mindpet/__init__.py
mindpet/mindpet_main.py
mindpet/mindpet_sdk.py
mindpet/delta/__init__.py
mindpet/delta/adapter.py
mindpet/delta/delta_constants.py
mindpet/delta/lora.py
mindpet/delta/low_rank_adapter.py
mindpet/delta/prefix_layer.py
mindpet/delta/ptuning2.py
mindpet/delta/r_drop.py
mindpet/graph/__init__.py
mindpet/graph/ckpt_util.py
mindpet/graph/freeze_utils.py
mindpet/layers/__init__.py
mindpet/layers/activation.py
mindpet/log/__init__.py
mindpet/log/log.py
mindpet/log/log_utils.py
mindpet/security/__init__.py
mindpet/security/param_check/__init__.py
mindpet/security/param_check/base_check.py
mindpet/security/param_check/model_config_params_check_util.py
mindpet/security/param_check/option_check_utils.py
mindpet/task/__init__.py
mindpet/task/option_decorators.py
mindpet/task/evaluate_infer/__init__.py
mindpet/task/evaluate_infer/evaluate_infer_task.py
mindpet/task/evaluate_infer/result_file_check.py
mindpet/task/finetune/__init__.py
mindpet/task/finetune/finetune_options_check.py
mindpet/task/finetune/finetune_task.py
mindpet/task/options/__init__.py
mindpet/task/options/boot_file_path_option.py
mindpet/task/options/ckpt_path_option.py
mindpet/task/options/data_path_option.py
mindpet/task/options/model_config_path_option.py
mindpet/task/options/output_path_option.py
mindpet/task/options/path_check_param.py
mindpet/task/options/pretrained_model_path_option.py
mindpet/task/options/quiet_option.py
mindpet/task/options/timeout_option.py
mindpet/utils/__init__.py
mindpet/utils/constants.py
mindpet/utils/entrance_monitor.py
mindpet/utils/exceptions.py
mindpet/utils/io_utils.py
mindpet/utils/task_utils.py
mindpet/utils/version_control.py
mindpet/utils/version_utils.py
mindpet-1.0.4.dist-info/LICENSE
mindpet-1.0.4.dist-info/METADATA
mindpet-1.0.4.dist-info/WHEEL
mindpet-1.0.4.dist-info/entry_points.txt
mindpet-1.0.4.dist-info/top_level.txt
mindpet-1.0.4.dist-info/RECORD
