Metadata-Version: 2.1
Name: mindpet
Version: 1.0.4
Summary: Parameter-Efficient Tuning
Home-page: UNKNOWN
License: UNKNOWN
Keywords: Parameter-Efficient Tuning
Platform: UNKNOWN
License-File: LICENSE
Requires-Dist: click
Requires-Dist: pyyaml
